deeptrust/__init__.py
deeptrust-0.0.1.dist-info/METADATA
deeptrust-0.0.1.dist-info/WHEEL
deeptrust-0.0.1.dist-info/top_level.txt
deeptrust-0.0.1.dist-info/RECORD
